xenum
