Metadata-Version: 1.1
Name: xenum
Version: 1.2
Summary: A simple alternative to Python 3 enums.
Home-page: https://github.com/lainproliant/xenum
Author: Lain Supe (lainproliant)
Author-email: lainproliant@gmail.com
License: BSD
Keywords: enum enums
Platform: UNKNOWN
Classifier: Development Status :: 4 - Beta
Classifier: Intended Audience :: Developers
Classifier: Topic :: Software Development :: Libraries
Classifier: License :: OSI Approved :: BSD License
Classifier: Programming Language :: Python :: 3
Classifier: Programming Language :: Python :: 3.2
Classifier: Programming Language :: Python :: 3.3
Classifier: Programming Language :: Python :: 3.4
Classifier: Programming Language :: Python :: 3.5
